cameo_mo/__init__.py
cameo_mo/bak_base.py
cameo_mo/base.py
cameo_mo/cameo_mo.py
cameo_mo-1.1.0.dist-info/METADATA
cameo_mo-1.1.0.dist-info/WHEEL
cameo_mo-1.1.0.dist-info/top_level.txt
cameo_mo-1.1.0.dist-info/RECORD
