Metadata-Version: 2.1
Name: cameo-mo
Version: 1.1.0
Summary: Let Molly can upload IOT data to cloud.
Home-page: https://github.com/bohachu/cameo_mo
Author: Bowen Chiu
Author-email: cbh@cameo.tw
License: UNKNOWN
Platform: UNKNOWN
Classifier: Programming Language :: Python :: 3
Classifier: License :: OSI Approved :: MIT License
Classifier: Operating System :: OS Independent
